LICENSE
MANIFEST.in
README.rst
setup.py
dist/django-news-sitemaps-0.1.5.tar.gz
django_news_sitemaps.egg-info/PKG-INFO
django_news_sitemaps.egg-info/SOURCES.txt
django_news_sitemaps.egg-info/dependency_links.txt
django_news_sitemaps.egg-info/top_level.txt
news_sitemaps/__init__.py
news_sitemaps/models.py
news_sitemaps/settings.py
news_sitemaps/sitemaps.py
news_sitemaps/tests.py
news_sitemaps/urls.py
news_sitemaps/views.py
news_sitemaps/templates/sitemaps/index.xml
news_sitemaps/templates/sitemaps/news_sitemap.xml