Metadata-Version: 1.0
Name: django-news-sitemaps
Version: 0.1.5
Summary: Generates sitemaps compatible with the Google News schema
Home-page: http://github.com/washingtontimes/django-news-sitemaps/
Author: TWT Web Devs
Author-email: webdev@washingtontimes.com
License: UNKNOWN
Platform: UNKNOWN
Classifier: Development Status :: 4 - Beta
Classifier: Environment :: Web Environment
Classifier: Framework :: Django
Classifier: Intended Audience :: Developers
Classifier: License :: OSI Approved :: Apache Software License
Classifier: Programming Language :: Python
Classifier: Operating System :: OS Independent
